demo/demo/__init__.py
demo/demo/settings.py
demo/demo/urls.py
demo/demo/wsgi.py
demo/test/__init__.py
demo/test/management/__init__.py
demo/test/management/commands/__init__.py
demo/test/management/commands/test_spider.py
django_proxylist_for_grab-0.5.1.dist-info/DESCRIPTION.rst
django_proxylist_for_grab-0.5.1.dist-info/METADATA
django_proxylist_for_grab-0.5.1.dist-info/metadata.json
django_proxylist_for_grab-0.5.1.dist-info/RECORD
django_proxylist_for_grab-0.5.1.dist-info/top_level.txt
django_proxylist_for_grab-0.5.1.dist-info/WHEEL
docs/__init__.py
docs/conf.py
proxylist/__init__.py
proxylist/admin.py
proxylist/apps.py
proxylist/defaults.py
proxylist/grabber.py
proxylist/models.py
proxylist/signals.py
proxylist/tasks.py
proxylist/test_cases.py
proxylist/test_settings.py
proxylist/urls.py
proxylist/views.py
proxylist/data/mobile_agents.txt
proxylist/data/pc_agents.txt
proxylist/locale/ru/LC_MESSAGES/django.mo
proxylist/locale/ru/LC_MESSAGES/django.po
proxylist/management/__init__.py
proxylist/management/commands/__init__.py
proxylist/management/commands/check_proxies.py
proxylist/management/commands/clean_proxies.py
proxylist/management/commands/fetch_proxies.py
proxylist/management/commands/grab_proxies.py
proxylist/management/commands/update_next_check.py
proxylist/management/commands/update_proxies.py
proxylist/migrations/0001_initial.py
proxylist/migrations/0002_auto__del_field_proxy_connection_time__del_field_proxy_ip_address__del.py
proxylist/migrations/0003_auto__add_field_proxy_elapsed_time.py
proxylist/migrations/0004_auto__add_field_proxy_created.py
proxylist/migrations/0005_auto__add_upload.py
proxylist/migrations/0006_auto__del_unique_proxy_hostname__add_unique_proxy_hostname_port.py
proxylist/migrations/0007_auto__add_proxylist.py
proxylist/migrations/0008_auto__add_index_proxy_errors_last_check__add_index_proxy_errors_last_c.py
proxylist/migrations/__init__.py
proxylist/templates/proxylist/admin/change_list_link.html
proxylist/templates/proxylist/admin/proxylist.html
