Metadata-Version: 2.0
Name: django-proxylist-for-grab
Version: 0.5.1
Summary: Proxy-list management application for Django
Home-page: https://github.com/gotlium/django-proxylist
Author: GoTLiuM InSPiRiT
Author-email: gotlium@gmail.com
License: GPL v3
Keywords: django proxylist grab
Platform: UNKNOWN
Classifier: Development Status :: 5 - Production/Stable
Classifier: Environment :: Console
Classifier: Environment :: Web Environment
Classifier: Framework :: Django
Classifier: Intended Audience :: Developers
Classifier: Intended Audience :: System Administrators
Classifier: License :: OSI Approved :: GNU General Public License v3 (GPLv3)
Classifier: Operating System :: OS Independent
Classifier: Programming Language :: Python
Classifier: Programming Language :: Python :: 2.6
Classifier: Programming Language :: Python :: 2.7
Classifier: Topic :: Internet :: Proxy Servers
Requires-Dist: django-countries (>=1.5)
Requires-Dist: python-dateutil
Requires-Dist: multiprocessing
Requires-Dist: pygeoip
Requires-Dist: celery
Requires-Dist: pycurl
Requires-Dist: lxml
Requires-Dist: grab
